dtool_http/__init__.py
dtool_http/publish.py
dtool_http/server.py
dtool_http/storagebroker.py
dtool_http/version.py
dtool_http-0.5.2.dist-info/licenses/LICENSE.rst
dtool_http-0.5.2.dist-info/METADATA
dtool_http-0.5.2.dist-info/WHEEL
dtool_http-0.5.2.dist-info/entry_points.txt
dtool_http-0.5.2.dist-info/top_level.txt
dtool_http-0.5.2.dist-info/RECORD
