Metadata-Version: 2.4
Name: dtool-http
Version: 0.5.2
Summary: Add HTTP read only dataset support to dtool
Author-email: Tjelvar Olsson <tjelvar.olsson@gmail.com>
Project-URL: Documentation, https://github.com/jic-dtool/dtool-http/blob/master/README.rst
Project-URL: Repository, https://github.com/jic-dtool/dtool-http
Project-URL: Changelog, https://github.com/jic-dtool/dtool-http/blob/master/CHANGELOG.rst
License-File: LICENSE.rst
Requires-Dist: dtoolcore>=3.13
Requires-Dist: requests
Provides-Extra: test
Requires-Dist: pytest; extra == "test"
Requires-Dist: pytest-cov; extra == "test"
Requires-Dist: pytz; extra == "test"
Dynamic: license-file
